householdsim/__init__.py
householdsim/model.py
householdsim/mosaik.py
tests/__init__.py
tests/test_model.py
tests/test_mosaik.py
mosaik_householdsim-2.1.0.dist-info/AUTHORS.txt
mosaik_householdsim-2.1.0.dist-info/LICENSE.txt
mosaik_householdsim-2.1.0.dist-info/METADATA
mosaik_householdsim-2.1.0.dist-info/WHEEL
mosaik_householdsim-2.1.0.dist-info/entry_points.txt
mosaik_householdsim-2.1.0.dist-info/top_level.txt
mosaik_householdsim-2.1.0.dist-info/RECORD
